{
    "word": "The victories gained by the Reformation stirred the Romanists to still more determined efforts for its overthrow. Seeing how little had been accomplished by persecution in suppressing Luther's work in Germany, they decided to meet the reform with its own weapons. They would hold a disputation with Zwingli, and having the arrangement of matters, they would make sure of victory by choosing, themselves, not only the place of the combat, but the judges that should decide between the disputants. And if they could once get Zwingli into their power, they would take care that he did not escape them. The leader silenced, the movement could speedily be crushed. This purpose, however, was carefully concealed.",
    "paragraph": 4,
    "bookcode": "GC",
    "page": 181,
    "chapter": "The Swiss Reformer",
    "chapterN": 9
}