{
    "word": "Frederick of Saxony maintained a studied reserve, carefully concealing his real feelings toward the Reformer, while at the same time he guarded him with tireless vigilance, watching all his movements and all those of his enemies. But there were many who made no attempt to conceal their sympathy with Luther. He was visited by princes, counts, barons, and other persons of distinction, both lay and ecclesiastical. \"The doctor's little room,\" wrote Spalatin, \"could not contain all the visitors who presented themselves.\"-- Martyn, vol. 1, p. 404. The people gazed upon him as if he were more than human. Even those who had no faith in his doctrines could not but admire that lofty integrity which led him to brave death rather than violate his conscience.",
    "paragraph": 1,
    "bookcode": "GC",
    "page": 165,
    "chapter": "Luther Before the Diet",
    "chapterN": 8,
    "author": "Ellen G. White",
    "booktitle": "The Great Controversy",
    "date_published": "1911",
    "copyright_info": "Public Domain"
}