{
    "word": "Those who received the light concerning the sanctuary and the immutability of the law of God were filled with joy and wonder as they saw the beauty and harmony of the system of truth that opened to their understanding. They desired that the light which appeared to them so precious might be imparted to all Christians; and they could not but believe that it would be joyfully accepted. But truths that would place them at variance with the world were not welcome to many who claimed to be followers of Christ. Obedience to the fourth commandment required a sacrifice from which the majority drew back.",
    "paragraph": 1,
    "bookcode": "GC",
    "page": 454,
    "chapter": "A Work of Reform",
    "chapterN": 26,
    "author": "Ellen G. White",
    "booktitle": "The Great Controversy",
    "date_published": "1911",
    "copyright_info": "Public Domain"
}