{
    "word": "Popery had become the world's despot. Kings and emperors bowed to the decrees of the Roman pontiff. The destinies of men, both for time and for eternity, seemed under his control. For hundreds of years the doctrines of Rome had been extensively and implicitly received, its rites reverently performed, its festivals generally observed. Its clergy were honored and liberally sustained. Never since has the Roman Church attained to greater dignity, magnificence, or power.",
    "paragraph": 1,
    "bookcode": "GC",
    "page": 60,
    "chapter": "An Era of Spiritual Darkness",
    "chapterN": 3,
    "author": "Ellen G. White",
    "booktitle": "The Great Controversy",
    "date_published": "1911",
    "copyright_info": "Public Domain"
}