{
    "word": "\"Moreover,\" Darius continued, \"I make a decree what ye shall do to the elders of these Jews for the building of this house of God: that of the king's goods, even of the tribute beyond the river, forthwith expenses be given unto these men, that they be not hindered. And that which they have need of, both young bullocks, and rams, and lambs, for the burnt offerings of the God of heaven, wheat, salt, wine, and oil, according to the appointment of the priests which are at Jerusalem, let it be given them day by day without fail: that they may offer sacrifices of sweet savors unto the God of heaven, and pray for the life of the king, and of his sons.\" Ezra 6:7-10.",
    "paragraph": 2,
    "bookcode": "PK",
    "page": 579,
    "chapter": "\"The Prophets of God Helping Them\"",
    "chapterN": "46",
    "author": "Ellen G. White",
    "booktitle": "Prophets and Kings",
    "date_published": "1917",
    "copyright_info": "Public Domain"
}