{
    "word": "Such were the conditions existing during the early part of the reign of Darius Hystaspes. Spiritually as well as temporally, the Israelites were in a pitiable state. So long had they murmured and doubted; so long had they chosen to make personal interests first, while viewing with apathy the Lord's temple in ruins, that many had lost sight of God's purpose in restoring them to Judea; and these were saying, \"The time is not come, the time that the Lord's house should be built.\" Haggai 1:2.",
    "paragraph": 2,
    "bookcode": "PK",
    "page": 573,
    "chapter": "\"The Prophets of God Helping Them\"",
    "chapterN": "46",
    "author": "Ellen G. White",
    "booktitle": "Prophets and Kings",
    "date_published": "1917",
    "copyright_info": "Public Domain"
}