{
    "word": "God's favor toward Israel had always been conditional on their obedience. At the foot of Sinai they had entered into covenant relationship with Him as His \"peculiar treasure. . . above all people.\" Solemnly they had promised to follow in the path of obedience. \"All that the Lord hath spoken we will do,\" they had said. Exodus 19:5, 8. And when, a few days afterward, God's law was spoken from Sinai, and additional instruction in the form of statutes and judgments was communicated through Moses, the Israelites with one voice had again promised, \"All the words which the Lord hath said will we do.\" At the ratification of the covenant, the people had once more united in declaring, \"All that the Lord hath said will we do, and be obedient,\" Exodus 24:3, 7. God had chosen Israel as His people, and they had chosen Him as their King.",
    "paragraph": 1,
    "bookcode": "PK",
    "page": 293,
    "chapter": "\"Destroyed for Lack of Knowledge\"",
    "chapterN": "24",
    "author": "Ellen G. White",
    "booktitle": "Prophets and Kings",
    "date_published": "1917",
    "copyright_info": "Public Domain"
}