{
    "word": "\"And King Rehoboam took counsel with the old men that had stood before Solomon his father while he yet lived, saying, What counsel give ye me to return answer to this people? And they spake unto him, saying, If thou be kind to this people, and please them, and speak good words to them, they will be thy servants forever.\" 2 Chronicles 10:3-7.",
    "paragraph": 2,
    "bookcode": "PK",
    "page": 89,
    "chapter": "The Rending of the Kingdom",
    "chapterN": "6",
    "author": "Ellen G. White",
    "booktitle": "Prophets and Kings",
    "date_published": "1917",
    "copyright_info": "Public Domain"
}