{
    "word": "As the prophet ceased speaking, the king commanded that he be awarded the promised honors; and in harmony with this, \"they clothed Daniel with scarlet, and put a chain of gold about his neck, and made a proclamation concerning him, that he should be the third ruler in the kingdom.\"",
    "paragraph": 4,
    "bookcode": "PK",
    "page": 530,
    "chapter": "The Unseen Watcher",
    "chapterN": "43",
    "author": "Ellen G. White",
    "booktitle": "Prophets and Kings",
    "date_published": "1917",
    "copyright_info": "Public Domain"
}