{
    "word": "In the proverbs of Solomon are outlined principles of holy living and high endeavor, principles that are heaven-born and that lead to godliness, principles that should govern every act of life. It was the wide dissemination of these principles, and the recognition of God as the One to whom all praise and honor belong, that made Solomon's early reign a time of moral uplift as well as of material prosperity.",
    "paragraph": 4,
    "bookcode": "PK",
    "page": 33,
    "chapter": "Solomon",
    "chapterN": "1",
    "author": "Ellen G. White",
    "booktitle": "Prophets and Kings",
    "date_published": "1917",
    "copyright_info": "Public Domain"
}