{
    "word": "At the close of the great papal persecution, Christ declared, the sun should be darkened, and the moon should not give her light. Next, the stars should fall from heaven. And He says, \"Learn a parable of the fig tree; When his branch is yet tender, and putteth forth leaves, ye know that summer is nigh: so likewise ye, when ye shall see all these things, know that He is near, even at the doors.\" Matthew 24:32, 33, margin.",
    "paragraph": 1,
    "bookcode": "DA",
    "page": 632,
    "chapter": "On the Mount of Olives",
    "chapterN": "69"
}