{
    "word": "The disciples awakened at the voice of Jesus, but they hardly knew Him, His face was so changed by anguish. Addressing Peter, Jesus said, \"Simon, sleepest thou? couldest not thou watch one hour? Watch ye and pray, lest ye enter into temptation. The spirit truly is ready, but the flesh is weak.\" The weakness of His disciples awakened the sympathy of Jesus. He feared that they would not be able to endure the test which would come upon them in His betrayal and death. He did not reprove them, but said, \"Watch ye and pray, lest ye enter into temptation.\" Even in His great agony, He was seeking to excuse their weakness. \"The spirit truly is ready,\" He said, \"but the flesh is weak.\"",
    "paragraph": 2,
    "bookcode": "DA",
    "page": 689,
    "chapter": "Gethsemane",
    "chapterN": "74"
}