{
    "word": "To the Pharisees and rulers this claim seemed an arrogant assumption. That a man like themselves should make such pretensions they could not tolerate. Seeming to ignore His words, they demanded, \"Who art Thou?\" They were bent upon forcing Him to declare Himself the Christ. His appearance and His work were so at variance with the expectations of the people, that, as His wily enemies believed, a direct announcement of Himself as the Messiah would cause Him to be rejected as an impostor.",
    "paragraph": 2,
    "bookcode": "DA",
    "page": 465,
    "chapter": "\"The Light of Life\"",
    "chapterN": "51"
}