{
    "word": "This act opened the minds of the disciples more fully to the labor that lay before them among the Gentiles. They saw a wide field of usefulness outside of Judea. They saw souls bearing sorrows unknown to those more highly favored. Among those whom they had been taught to despise were souls longing for help from the mighty Healer, hungering for the light of truth, which had been so abundantly given to the Jews.",
    "paragraph": 4,
    "bookcode": "DA",
    "page": 402,
    "chapter": "Barriers Broken Down",
    "chapterN": "43"
}