{
    "word": "The sight of that pale, suffering face, those quivering lips, that look of compassion and forgiveness, pierced his heart like an arrow. Conscience was aroused. Memory was active. Peter called to mind his promise of a few short hours before that he would go with his Lord to prison and to death. He remembered his grief when the Saviour told him in the upper chamber that he would deny his Lord thrice that same night. Peter had just declared that he knew not Jesus, but he now realized with bitter grief how well his Lord knew him, and how accurately He had read his heart, the falseness of which was unknown even to himself.",
    "paragraph": 1,
    "bookcode": "DA",
    "page": 713,
    "chapter": "Before Annas and the Court of Caiaphas",
    "chapterN": "75"
}