{
    "word": "It was a false conception of the Messiah's work, and a lack of faith in the divine character of Jesus, that had led His brothers to urge Him to present Himself publicly to the people at the Feast of Tabernacles. Now, in a spirit akin to this, the disciples would have prevented Him from making the journey to Jerusalem. They remembered His words concerning what was to befall Him there, they knew the deadly hostility of the religious leaders, and they would fain have dissuaded their Master from going thither.",
    "paragraph": 4,
    "bookcode": "DA",
    "page": 485,
    "chapter": "The Last Journey From Galilee",
    "chapterN": "53"
}