{
    "word": "Pilate had a desire to know the truth. His mind was confused. He eagerly grasped the words of the Saviour, and his heart was stirred with a great longing to know what it really was, and how he could obtain it. \"What is truth?\" he inquired. But he did not wait for an answer. The tumult outside recalled him to the interests of the hour; for the priests were clamorous for immediate action. Going out to the Jews, he declared emphatically, \"I find in Him no fault at all.\"",
    "paragraph": 4,
    "bookcode": "DA",
    "page": 727,
    "chapter": "In Pilate's Judgment Hall",
    "chapterN": "77"
}