{
    "word": "The multitudes were amazed at this teaching, which was so at variance with the precepts and example of the Pharisees. The people had come to think that happiness consisted in the possession of the things of this world, and that fame and the honor of men were much to be coveted. It was very pleasing to be called \"Rabbi,\" and to be extolled as wise and religious, having their virtues paraded before the public. This was regarded as the crown of happiness. But in the presence of that vast throng, Jesus declared that earthly gain and honor were all the reward such persons would ever receive. He spoke with certainty, and a convincing power attended His words. The people were silenced, and a feeling of fear crept over them. They looked at one another doubtfully. Who of them would be saved if this Man's teachings were true? Many were convicted that this remarkable Teacher was actuated by the Spirit of God, and that the sentiments He uttered were divine.",
    "paragraph": 1,
    "bookcode": "DA",
    "page": 305,
    "chapter": "The Sermon on the Mount",
    "chapterN": "31"
}