{
    "word": "The Pharisees prided themselves on their obedience to the law; yet they knew so little of its principles through everyday practice that to them the Saviour's words sounded like heresy. As He swept away the rubbish under which the truth had been buried, they thought He was sweeping away the truth itself. They whispered to one another that He was making light of the law. He read their thoughts, and answered them, saying,--",
    "paragraph": 3,
    "bookcode": "DA",
    "page": 307,
    "chapter": "The Sermon on the Mount",
    "chapterN": "31"
}