{
    "word": "As Christ arose, He brought from the grave a multitude of captives. The earthquake at His death had rent open their graves, and when He arose, they came forth with Him. They were those who had been co-laborers with God, and who at the cost of their lives had borne testimony to the truth. Now they were to be witnesses for Him who had raised them from the dead.",
    "paragraph": 1,
    "bookcode": "DA",
    "page": 786,
    "chapter": "\"The Lord Is Risen\"",
    "chapterN": "81"
}