{
    "word": "The priests and rulers could not but give a correct answer to Christ's question, and thus He obtained their opinion in favor of the first son. This son represented the publicans, those who were despised and hated by the Pharisees. The publicans had been grossly immoral. They had indeed been transgressors of the law of God, showing in their lives an absolute resistance to His requirements. They had been unthankful and unholy; when told to go and work in the Lord's vineyard, they had given a contemptuous refusal. But when John came, preaching repentance and baptism, the publicans received his message and were baptized.",
    "paragraph": 3,
    "bookcode": "DA",
    "page": 595,
    "chapter": "The Temple Cleansed Again",
    "chapterN": "65"
}