{
    "word": "With intense interest the multitude awaited the decision. They knew that the priests had professed to accept the ministry of John, and they expected them to acknowledge without a question that he was sent from God. But after conferring secretly together, the priests decided not to commit themselves. Hypocritically professing ignorance, they said, \"We cannot tell.\" \"Neither tell I you,\" said Christ, \"by what authority I do these things.\"",
    "paragraph": 1,
    "bookcode": "DA",
    "page": 594,
    "chapter": "The Temple Cleansed Again",
    "chapterN": "65"
}