{
    "word": "Many earnestly desired to return to the purity and simplicity which characterized the primitive church. They regarded many of the established customs of the English Church as monuments of idolatry, and they could not in conscience unite in her worship. But the church, being supported by the civil authority, would permit no dissent from her forms. Attendance upon her service was required by law, and unauthorized assemblies for religious worship were prohibited, under penalty of imprisonment, exile, and death.",
    "paragraph": 1,
    "bookcode": "GC",
    "page": 290,
    "chapter": "The Pilgrim Fathers",
    "chapterN": 16,
    "author": "Ellen G. White",
    "booktitle": "The Great Controversy",
    "date_published": "1911",
    "copyright_info": "Public Domain"
}