{
    "word": "With the opening of the Great Reformation came the writings of Luther, and then Tyndale's English New Testament. Unnoticed by the hierarchy, these messengers silently traversed the mountains and valleys, kindling into new life the torch of truth so nearly extinguished in Scotland, and undoing the work which Rome for four centuries of oppression had done.",
    "paragraph": 3,
    "bookcode": "GC",
    "page": 249,
    "chapter": "Later English Reformers",
    "chapterN": 14,
    "author": "Ellen G. White",
    "booktitle": "The Great Controversy",
    "date_published": "1911",
    "copyright_info": "Public Domain"
}